regidi-0.1.0.dist-info/METADATA
regidi-0.1.0.dist-info/WHEEL
regidi-0.1.0.dist-info/entry_points.txt
regidi-0.1.0.dist-info/licenses/LICENSE
regidi/__init__.py
regidi/__main__.py
regidi/reverse.py
regidi/substitution/__init__.py
regidi/substitution/aux5-mapping.csv
regidi/substitution/base6-blocklist.bin
regidi/utils.py
regidi-0.1.0.dist-info/RECORD
