Metadata-Version: 2.1
Name: regidi
Version: 0.1.0
Summary: Readable Gibberish Digests
Author-Email: Jakob Sundh <jsundh@users.noreply.github.com>
License: MIT
Requires-Python: >=3.12
Requires-Dist: bitarray>=2.9.2
